{"cameraMode":{"drawMode":0,"name":"Shaded","section":"Shading Mode"},"sceneLighting":true,"audioPlay":false,"sceneViewState":{"m_AlwaysRefresh":false,"showFog":true,"showSkybox":true,"showFlares":true,"showImageEffects":true,"showParticleSystems":true,"showVisualEffectGraphs":true,"m_FxEnabled":true},"in2DMode":false,"pivot":{"x":9.10461711883545,"y":7.266763210296631,"z":-2.5302038192749025},"rotation":{"x":-0.024586118757724763,"y":-0.9154463410377502,"z":0.39253711700439455,"w":-0.08698181062936783},"size":5.518901824951172,"orthographic":false}